macgputils/__init__.py
macgputils/core.py
macgputils-0.1.2.dist-info/METADATA
macgputils-0.1.2.dist-info/WHEEL
macgputils-0.1.2.dist-info/top_level.txt
macgputils-0.1.2.dist-info/RECORD
